<?xml version="1.0" encoding="UTF-8"?>
<nite:root xmlns:nite="http://nite.sourceforge.net/" id="124419006.unit.b">
<word id="124419006.b.unit.2">hello</word>
<word id="124419006.b.unit.3">it's</word>
<stdzcode id="124419006.b.unit.4" description="name"/>
<word id="124419006.b.unit.5">from</word>
<pncode type="business" id="124419006.b.unit.6"/>
<pncode type="business" id="124419006.b.unit.7"/>
<pncode type="business" id="124419006.b.unit.8"/>
<word id="124419006.b.unit.9">in</word>
<pncode type="town" id="124419006.b.unit.10"/>
<word id="124419006.b.unit.12">hello</word>
<word id="124419006.b.unit.13">i've</word>
<word id="124419006.b.unit.14">a</word>
<word id="124419006.b.unit.15">gentleman</word>
<word id="124419006.b.unit.16">in</word>
<word id="124419006.b.unit.17">wishing</word>
<word id="124419006.b.unit.18">to</word>
<word id="124419006.b.unit.19">take</word>
<word id="124419006.b.unit.20">over</word>
<word id="124419006.b.unit.21">a</word>
<word id="124419006.b.unit.22">line</word>
<word id="124419006.b.unit.23">please</word>
<word id="124419006.b.unit.30">it's</word>
<word id="124419006.b.unit.31">just</word>
<word id="124419006.b.unit.32">on</word>
<word id="124419006.b.unit.33">a</word>
<word id="124419006.b.unit.34">normal</word>
<word id="124419006.b.unit.35">standard</word>
<word id="124419006.b.unit.36">line</word>
<word id="124419006.b.unit.44">he</word>
<word id="124419006.b.unit.45">not</word>
<word id="124419006.b.unit.46">at</word>
<word id="124419006.b.unit.47">this</word>
<word id="124419006.b.unit.48">he</word>
<word id="124419006.b.unit.49">has</word>
<word id="124419006.b.unit.50">one</word>
<word id="124419006.b.unit.51">to</word>
<word id="124419006.b.unit.52">prove</word>
<word id="124419006.b.unit.53">his</word>
<word id="124419006.b.unit.54">address</word>
<word id="124419006.b.unit.55">yes</word>
<word id="124419006.b.unit.77">yeah</word>
<word id="124419006.b.unit.78">it's</word>
<partword id="124419006.b.unit.79">num</partword>
<word id="124419006.b.unit.80">it's</word>
<word id="124419006.b.unit.81">number</word>
<num id="124419006.b.unit.82"/>
<pncode type="road" id="124419006.b.unit.84"/>
<pncode type="road" id="124419006.b.unit.85"/>
<word id="124419006.b.unit.88">yes</word>
<sil BTlength="" id="124419006.b.unit.89"/>
<word id="124419006.b.unit.90">that's</word>
<pncode type="region" id="124419006.b.unit.91"/>
<pncode type="town" id="124419006.b.unit.92"/>
</nite:root>
