<?xml version="1.0" encoding="UTF-8"?>
<nite:root xmlns:nite="http://nite.sourceforge.net/" id="130254010.unit.a">
<stdzcode id="130254010.a.unit.1" description="name"/>
<word id="130254010.a.unit.27">oh</word>
<word id="130254010.a.unit.28">right</word>
<word id="130254010.a.unit.45">oh</word>
<word id="130254010.a.unit.46">yeah</word>
<word id="130254010.a.unit.110">oh</word>
<word id="130254010.a.unit.111">right</word>
<word id="130254010.a.unit.112">yeah</word>
<word id="130254010.a.unit.173">yeah</word>
<word id="130254010.a.unit.174">okay</word>
<word id="130254010.a.unit.175">what's</word>
<partword id="130254010.a.unit.176">yo</partword>
<word id="130254010.a.unit.182">i</word>
<word id="130254010.a.unit.183">wouldn't</word>
<word id="130254010.a.unit.184">have</word>
<word id="130254010.a.unit.185">thought</word>
<word id="130254010.a.unit.186">so</word>
<word id="130254010.a.unit.187">d'you</word>
</nite:root>
