<?xml version="1.0" encoding="UTF-8"?>
<nite:root xmlns:nite="http://nite.sourceforge.net/" id="130348007.unit.b">
<word id="130348007.b.unit.2">hello</word>
<word id="130348007.b.unit.3">em</word>
<word id="130348007.b.unit.4">i'm</word>
<word id="130348007.b.unit.5">speaking</word>
<word id="130348007.b.unit.6">on</word>
<word id="130348007.b.unit.7">the</word>
<word id="130348007.b.unit.8">behalf</word>
<word id="130348007.b.unit.9">of</word>
<word id="130348007.b.unit.10">my</word>
<word id="130348007.b.unit.11">wife</word>
<word id="130348007.b.unit.12">um</word>
<stdzcode id="130348007.b.unit.13" description="name"/>
<stdzcode id="130348007.b.unit.14" description="name"/>
<word id="130348007.b.unit.15">she's</word>
<word id="130348007.b.unit.16">she's</word>
<word id="130348007.b.unit.17">just</word>
<word id="130348007.b.unit.18">been</word>
<word id="130348007.b.unit.19">put</word>
<word id="130348007.b.unit.20">on</word>
<word id="130348007.b.unit.21">the</word>
<word id="130348007.b.unit.22">phone</word>
<word id="130348007.b.unit.23">in</word>
<word id="130348007.b.unit.24">the</word>
<word id="130348007.b.unit.25">last</word>
<word id="130348007.b.unit.26">couple</word>
<word id="130348007.b.unit.27">of</word>
<word id="130348007.b.unit.28">days</word>
<word id="130348007.b.unit.30">and</word>
<word id="130348007.b.unit.31">the</word>
<word id="130348007.b.unit.32">thing</word>
<word id="130348007.b.unit.33">is</word>
<word id="130348007.b.unit.34">like</word>
<word id="130348007.b.unit.35">she's</word>
<word id="130348007.b.unit.36">she's</word>
<word id="130348007.b.unit.37">renting</word>
<word id="130348007.b.unit.38">a</word>
<word id="130348007.b.unit.39">um</word>
<word id="130348007.b.unit.40">a</word>
<word id="130348007.b.unit.41">cordless</word>
<word id="130348007.b.unit.42">phone</word>
<word id="130348007.b.unit.43">off</word>
<word id="130348007.b.unit.44">you</word>
<word id="130348007.b.unit.45">at</word>
<word id="130348007.b.unit.46">the</word>
<word id="130348007.b.unit.47">moment</word>
<word id="130348007.b.unit.49">but</word>
<word id="130348007.b.unit.50">the</word>
<word id="130348007.b.unit.51">property</word>
<word id="130348007.b.unit.52">she's</word>
<word id="130348007.b.unit.53">moved</word>
<word id="130348007.b.unit.54">into</word>
<word id="130348007.b.unit.55">is</word>
<partword id="130348007.b.unit.56">th</partword>
<partword id="130348007.b.unit.57">the</partword>
<word id="130348007.b.unit.58">there</word>
<word id="130348007.b.unit.59">was</word>
<word id="130348007.b.unit.60">already</word>
<word id="130348007.b.unit.61">a</word>
<word id="130348007.b.unit.62">box</word>
<word id="130348007.b.unit.63">you</word>
<word id="130348007.b.unit.64">know</word>
<word id="130348007.b.unit.65">in</word>
<word id="130348007.b.unit.66">the</word>
<word id="130348007.b.unit.67">flat</word>
<word id="130348007.b.unit.69">but</word>
<word id="130348007.b.unit.70">the</word>
<word id="130348007.b.unit.71">thing</word>
<word id="130348007.b.unit.72">is</word>
<word id="130348007.b.unit.73">it's</word>
<word id="130348007.b.unit.74">very</word>
<word id="130348007.b.unit.75">hard</word>
<word id="130348007.b.unit.76">to</word>
<word id="130348007.b.unit.77">uh</word>
<word id="130348007.b.unit.78">get</word>
<word id="130348007.b.unit.79">the</word>
<word id="130348007.b.unit.80">uh</word>
<word id="130348007.b.unit.81">to</word>
<word id="130348007.b.unit.82">to</word>
<word id="130348007.b.unit.83">plug</word>
<word id="130348007.b.unit.84">the</word>
<word id="130348007.b.unit.85">adaptor</word>
<word id="130348007.b.unit.86">into</word>
<word id="130348007.b.unit.87">electric</word>
<word id="130348007.b.unit.88">socket</word>
<word id="130348007.b.unit.89">where</word>
<word id="130348007.b.unit.90">the</word>
<word id="130348007.b.unit.91">box</word>
<word id="130348007.b.unit.92">is</word>
<word id="130348007.b.unit.93">situated</word>
<word id="130348007.b.unit.94">in</word>
<word id="130348007.b.unit.95">the</word>
<word id="130348007.b.unit.96">flat</word>
<word id="130348007.b.unit.98">now</word>
<word id="130348007.b.unit.99">what's</word>
<word id="130348007.b.unit.100">she</word>
<partword id="130348007.b.unit.101">wan</partword>
<word id="130348007.b.unit.102">she's</word>
<partword id="130348007.b.unit.103">ask</partword>
<word id="130348007.b.unit.104">asked</word>
<word id="130348007.b.unit.105">me</word>
<word id="130348007.b.unit.106">to</word>
<word id="130348007.b.unit.107">phone</word>
<word id="130348007.b.unit.108">you</word>
<word id="130348007.b.unit.109">and</word>
<word id="130348007.b.unit.110">ask</word>
<word id="130348007.b.unit.111">you</word>
<word id="130348007.b.unit.112">would</word>
<word id="130348007.b.unit.113">it</word>
<word id="130348007.b.unit.114">cost</word>
<word id="130348007.b.unit.115">her</word>
<word id="130348007.b.unit.116">anything</word>
<word id="130348007.b.unit.117">for</word>
<pncode type="business" id="130348007.b.unit.118"/>
<pncode type="business" id="130348007.b.unit.119"/>
<partword id="130348007.b.unit.120">t</partword>
<partword id="130348007.b.unit.121">t</partword>
<word id="130348007.b.unit.122">to</word>
<word id="130348007.b.unit.123">put</word>
<word id="130348007.b.unit.124">another</word>
<word id="130348007.b.unit.125">box</word>
<word id="130348007.b.unit.126">into</word>
<word id="130348007.b.unit.127">this</word>
<word id="130348007.b.unit.128">flat</word>
<comment text="agent_clears_throat" id="130348007.b.unit.129"/>
<word id="130348007.b.unit.130">cause</word>
<word id="130348007.b.unit.131">she</word>
<word id="130348007.b.unit.132">didn't</word>
<word id="130348007.b.unit.133">originally</word>
<word id="130348007.b.unit.134">apply</word>
<word id="130348007.b.unit.135">for</word>
<word id="130348007.b.unit.136">a</word>
<word id="130348007.b.unit.137">box</word>
<word id="130348007.b.unit.138">there</word>
<word id="130348007.b.unit.139">was</word>
<word id="130348007.b.unit.140">already</word>
<word id="130348007.b.unit.141">one</word>
<word id="130348007.b.unit.142">here</word>
<word id="130348007.b.unit.143">when</word>
<word id="130348007.b.unit.144">she</word>
<word id="130348007.b.unit.145">asked</word>
<word id="130348007.b.unit.146">to</word>
<word id="130348007.b.unit.147">be</word>
<word id="130348007.b.unit.148">put</word>
<word id="130348007.b.unit.149">on</word>
<word id="130348007.b.unit.150">the</word>
<word id="130348007.b.unit.151">phone</word>
<word id="130348007.b.unit.179">oh</word>
<word id="130348007.b.unit.180">no</word>
<word id="130348007.b.unit.181">couldn't</word>
<word id="130348007.b.unit.182">of</word>
<word id="130348007.b.unit.183">no</word>
<word id="130348007.b.unit.184">she</word>
<word id="130348007.b.unit.185">couldn't</word>
<word id="130348007.b.unit.186">afford</word>
<word id="130348007.b.unit.187">that</word>
<word id="130348007.b.unit.188">you</word>
<word id="130348007.b.unit.189">know</word>
<word id="130348007.b.unit.190">what</word>
<word id="130348007.b.unit.191">i</word>
<word id="130348007.b.unit.192">mean</word>
<word id="130348007.b.unit.231">yes</word>
<word id="130348007.b.unit.247">yes</word>
<word id="130348007.b.unit.278">no</word>
<partword id="130348007.b.unit.279">be..</partword>
<word id="130348007.b.unit.280">because</word>
<word id="130348007.b.unit.281">she</word>
<word id="130348007.b.unit.282">wasn't</word>
<word id="130348007.b.unit.283">quite</word>
<word id="130348007.b.unit.284">sure</word>
<word id="130348007.b.unit.285">you</word>
<word id="130348007.b.unit.286">know</word>
<word id="130348007.b.unit.287">with</word>
<word id="130348007.b.unit.288">the</word>
<word id="130348007.b.unit.289">phone</word>
<word id="130348007.b.unit.290">she's</word>
<word id="130348007.b.unit.291">she's</word>
<word id="130348007.b.unit.292">buying</word>
<word id="130348007.b.unit.293">off</word>
<word id="130348007.b.unit.294">of</word>
<pncode type="business" id="130348007.b.unit.295"/>
<pncode type="business" id="130348007.b.unit.296"/>
<bcanchor id="130348007.bcanchorb.3"><nite:pointer href="130348007.a.lturn.xml#id(130348007.lturn.14.1)" role="bc"/></bcanchor>
<word id="130348007.b.unit.298">the</word>
<word id="130348007.b.unit.299">cordless</word>
<word id="130348007.b.unit.300">one</word>
<word id="130348007.b.unit.301">if</word>
<word id="130348007.b.unit.302">um</word>
<word id="130348007.b.unit.303">she</word>
<word id="130348007.b.unit.304">could</word>
<word id="130348007.b.unit.305">use</word>
<word id="130348007.b.unit.306">this</word>
<word id="130348007.b.unit.307">phone</word>
<word id="130348007.b.unit.308">with</word>
<partword id="130348007.b.unit.309">w</partword>
<partword id="130348007.b.unit.310">w</partword>
<word id="130348007.b.unit.311">without</word>
<word id="130348007.b.unit.312">using</word>
<word id="130348007.b.unit.313">the</word>
<word id="130348007.b.unit.314">adaptor</word>
<word id="130348007.b.unit.315">or</word>
<word id="130348007.b.unit.316">the</word>
</nite:root>
