<?xml version="1.0" encoding="UTF-8"?>
<nite:root xmlns:nite="http://nite.sourceforge.net/" id="131255007.unit.b">
<word id="131255007.b.unit.2">yeah</word>
<word id="131255007.b.unit.3">i</word>
<word id="131255007.b.unit.4">got</word>
<word id="131255007.b.unit.5">the</word>
<word id="131255007.b.unit.6">money</word>
<word id="131255007.b.unit.8">uh</word>
<word id="131255007.b.unit.9">uh</word>
<word id="131255007.b.unit.10">uh</word>
<word id="131255007.b.unit.11">hello</word>
<word id="131255007.b.unit.14">i</word>
<word id="131255007.b.unit.15">i</word>
<word id="131255007.b.unit.16">i'd</word>
<word id="131255007.b.unit.17">like</word>
<word id="131255007.b.unit.18">i</word>
<word id="131255007.b.unit.19">i'd</word>
<word id="131255007.b.unit.20">like</word>
<word id="131255007.b.unit.21">uh</word>
<word id="131255007.b.unit.22">to</word>
<word id="131255007.b.unit.23">call</word>
<word id="131255007.b.unit.24">to</word>
<word id="131255007.b.unit.25">apply</word>
<word id="131255007.b.unit.26">for</word>
<word id="131255007.b.unit.27">telephone</word>
<word id="131255007.b.unit.28">service</word>
<word id="131255007.b.unit.29">in</word>
<word id="131255007.b.unit.30">my</word>
<sil BTlength="" id="131255007.b.unit.31"/>
<word id="131255007.b.unit.32">rented</word>
<partword id="131255007.b.unit.33">hou</partword>
<word id="131255007.b.unit.34">uh</word>
<word id="131255007.b.unit.35">rented</word>
<word id="131255007.b.unit.36">flat</word>
<word id="131255007.b.unit.43">uh</word>
<word id="131255007.b.unit.44">pardon</word>
<word id="131255007.b.unit.49">i</word>
<word id="131255007.b.unit.50">want</word>
<word id="131255007.b.unit.51">to</word>
<word id="131255007.b.unit.52">apply</word>
<word id="131255007.b.unit.53">i</word>
<word id="131255007.b.unit.54">want</word>
<word id="131255007.b.unit.55">to</word>
<word id="131255007.b.unit.56">get</word>
<word id="131255007.b.unit.57">uh</word>
<word id="131255007.b.unit.58">some</word>
<word id="131255007.b.unit.59">maybe</word>
<word id="131255007.b.unit.60">i</word>
<word id="131255007.b.unit.61">need</word>
<word id="131255007.b.unit.62">to</word>
<word id="131255007.b.unit.63">fill</word>
<word id="131255007.b.unit.64">in</word>
<word id="131255007.b.unit.65">some</word>
<word id="131255007.b.unit.66">you</word>
<word id="131255007.b.unit.67">telephone</word>
<word id="131255007.b.unit.68">me</word>
<word id="131255007.b.unit.89">uh</word>
<word id="131255007.b.unit.90">yeah</word>
<word id="131255007.b.unit.91">a</word>
<word id="131255007.b.unit.92">uh</word>
<partword id="131255007.b.unit.93">t</partword>
<word id="131255007.b.unit.94">pardon</word>
<word id="131255007.b.unit.107">i've</word>
<word id="131255007.b.unit.108">not</word>
<word id="131255007.b.unit.109">yet</word>
<word id="131255007.b.unit.110">it's</word>
<word id="131255007.b.unit.111">the</word>
<word id="131255007.b.unit.112">first</word>
<word id="131255007.b.unit.113">time</word>
<word id="131255007.b.unit.114">to</word>
<word id="131255007.b.unit.115">call</word>
</nite:root>
