<?xml version="1.0" encoding="UTF-8"?>
<nite:root xmlns:nite="http://nite.sourceforge.net/" id="le204040.unit.b">
<word id="le204040.b.unit.2">er</word>
<word id="le204040.b.unit.3">good</word>
<word id="le204040.b.unit.4">morning</word>
<word id="le204040.b.unit.5">um</word>
<word id="le204040.b.unit.6">i</word>
<word id="le204040.b.unit.7">wonder</word>
<word id="le204040.b.unit.8">if</word>
<word id="le204040.b.unit.9">you</word>
<word id="le204040.b.unit.10">can</word>
<word id="le204040.b.unit.11">help</word>
<word id="le204040.b.unit.12">me</word>
<word id="le204040.b.unit.13">please</word>
<word id="le204040.b.unit.14">we've</word>
<word id="le204040.b.unit.15">got</word>
<word id="le204040.b.unit.16">callminder</word>
<word id="le204040.b.unit.17">on</word>
<word id="le204040.b.unit.18">our</word>
<word id="le204040.b.unit.19">telephone</word>
<word id="le204040.b.unit.20">and</word>
<word id="le204040.b.unit.21">um</word>
<sil BTlength="" id="le204040.b.unit.22"/>
<word id="le204040.b.unit.23">uh</word>
<word id="le204040.b.unit.24">could</word>
<word id="le204040.b.unit.25">you</word>
<partword id="le204040.b.unit.26">possi</partword>
<sil BTlength="" id="le204040.b.unit.27"/>
<word id="le204040.b.unit.28">possibly</word>
<word id="le204040.b.unit.29">remind</word>
<word id="le204040.b.unit.30">me</word>
<word id="le204040.b.unit.31">how</word>
<word id="le204040.b.unit.32">to</word>
<word id="le204040.b.unit.33">access</word>
<word id="le204040.b.unit.34">messages</word>
<word id="le204040.b.unit.35">when</word>
<word id="le204040.b.unit.36">we're</word>
<word id="le204040.b.unit.37">out</word>
<sil BTlength="" id="le204040.b.unit.38"/>
<word id="le204040.b.unit.39">or</word>
<word id="le204040.b.unit.40">or</word>
<word id="le204040.b.unit.41">do</word>
<word id="le204040.b.unit.42">i</word>
<word id="le204040.b.unit.43">need</word>
<word id="le204040.b.unit.44">another</word>
<word id="le204040.b.unit.45">number</word>
<word id="le204040.b.unit.51">mm</word>
<word id="le204040.b.unit.62">thank</word>
<word id="le204040.b.unit.63">you</word>
<word id="le204040.b.unit.75">mmmm</word>
<word id="le204040.b.unit.76"/>
<word id="le204040.b.unit.82">yes</word>
<word id="le204040.b.unit.88">ring</word>
<word id="le204040.b.unit.89">own</word>
<word id="le204040.b.unit.90">number</word>
<word id="le204040.b.unit.91">yeah</word>
<word id="le204040.b.unit.96">star</word>
<word id="le204040.b.unit.97">star</word>
<word id="le204040.b.unit.104">right</word>
<word id="le204040.b.unit.105">um</word>
<word id="le204040.b.unit.106">i</word>
<word id="le204040.b.unit.107">think</word>
<word id="le204040.b.unit.108">i</word>
<word id="le204040.b.unit.109">remember</word>
<word id="le204040.b.unit.110">what</word>
<word id="le204040.b.unit.111">it</word>
<word id="le204040.b.unit.112">is</word>
<word id="le204040.b.unit.113">is</word>
<word id="le204040.b.unit.114">there</word>
<word id="le204040.b.unit.115">any</word>
<word id="le204040.b.unit.116">way</word>
<word id="le204040.b.unit.117">i</word>
<word id="le204040.b.unit.118">can</word>
<word id="le204040.b.unit.119">ring</word>
<word id="le204040.b.unit.120">somebody</word>
<word id="le204040.b.unit.121">to</word>
<word id="le204040.b.unit.122">check</word>
<word id="le204040.b.unit.123">i've</word>
<word id="le204040.b.unit.124">got</word>
<word id="le204040.b.unit.125">the</word>
<word id="le204040.b.unit.126">right</word>
<word id="le204040.b.unit.127">one</word>
<word id="le204040.b.unit.128">if</word>
<word id="le204040.b.unit.129">i</word>
<word id="le204040.b.unit.130">tell</word>
<word id="le204040.b.unit.131">them</word>
<word id="le204040.b.unit.132">what</word>
<word id="le204040.b.unit.133">it</word>
<word id="le204040.b.unit.134">is</word>
<word id="le204040.b.unit.146">but</word>
<word id="le204040.b.unit.147">they</word>
<word id="le204040.b.unit.148">must</word>
<word id="le204040.b.unit.149">have</word>
<word id="le204040.b.unit.150">a</word>
<word id="le204040.b.unit.151">record</word>
<word id="le204040.b.unit.152">of</word>
<word id="le204040.b.unit.153">that</word>
<word id="le204040.b.unit.154">mustn't</word>
<word id="le204040.b.unit.155">they</word>
<word id="le204040.b.unit.165">there</word>
<word id="le204040.b.unit.166">isn't</word>
<word id="le204040.b.unit.173">okay</word>
<word id="le204040.b.unit.174">what</word>
<word id="le204040.b.unit.175">number</word>
<word id="le204040.b.unit.176">do</word>
<word id="le204040.b.unit.177">i</word>
<word id="le204040.b.unit.178">have</word>
<word id="le204040.b.unit.179">to</word>
<word id="le204040.b.unit.180">ring</word>
<word id="le204040.b.unit.181">if</word>
<word id="le204040.b.unit.182">i</word>
<word id="le204040.b.unit.183">want</word>
<word id="le204040.b.unit.184">to</word>
<word id="le204040.b.unit.185">find</word>
<word id="le204040.b.unit.186">that</word>
<word id="le204040.b.unit.187">out</word>
<word id="le204040.b.unit.205">right</word>
<word id="le204040.b.unit.210">oh</word>
<word id="le204040.b.unit.211">that's</word>
<word id="le204040.b.unit.212">lovely</word>
<word id="le204040.b.unit.213">thank</word>
<word id="le204040.b.unit.214">you</word>
<bcanchor id="le204040.bcanchorb.8"><nite:pointer href="le204040.a.lturn.xml#id(le204040.lturn.12.1)" role="bc"/></bcanchor>
<word id="le204040.b.unit.217">very</word>
<word id="le204040.b.unit.218">much</word>
<word id="le204040.b.unit.219">bye</word>
<word id="le204040.b.unit.220">bye</word>
</nite:root>
