<?xml version="1.0" encoding="UTF-8"?>
<nite:root xmlns:nite="http://nite.sourceforge.net/" id="le703040.unit.b">
<word id="le703040.b.unit.2">oh</word>
<word id="le703040.b.unit.3">is</word>
<word id="le703040.b.unit.4">that</word>
<word id="le703040.b.unit.5">the</word>
<word id="le703040.b.unit.6">operator</word>
<word id="le703040.b.unit.10">i'd</word>
<word id="le703040.b.unit.11">like</word>
<word id="le703040.b.unit.12">to</word>
<word id="le703040.b.unit.13">book</word>
<word id="le703040.b.unit.14">an</word>
<word id="le703040.b.unit.15">alarm</word>
<word id="le703040.b.unit.16">call</word>
<word id="le703040.b.unit.17">for</word>
<word id="le703040.b.unit.18">tomorrow</word>
<word id="le703040.b.unit.19">morning</word>
<word id="le703040.b.unit.20">please</word>
<word id="le703040.b.unit.24">nine</word>
<word id="le703040.b.unit.25">a</word>
<word id="le703040.b.unit.26">m</word>
<word id="le703040.b.unit.27">please</word>
<word id="le703040.b.unit.33">oh</word>
<word id="le703040.b.unit.34">well</word>
<word id="le703040.b.unit.35">i</word>
<word id="le703040.b.unit.36">suppose</word>
<word id="le703040.b.unit.37">you</word>
<word id="le703040.b.unit.38">would</word>
<word id="le703040.b.unit.39">call</word>
<word id="le703040.b.unit.40">it</word>
<word id="le703040.b.unit.41">today</word>
<word id="le703040.b.unit.42">you're</word>
<word id="le703040.b.unit.43">quite</word>
<word id="le703040.b.unit.44">right</word>
<word id="le703040.b.unit.45">i</word>
<word id="le703040.b.unit.46">hadn't</word>
<word id="le703040.b.unit.47">realised</word>
<word id="le703040.b.unit.48">how</word>
<word id="le703040.b.unit.49">late</word>
<word id="le703040.b.unit.50">it</word>
<word id="le703040.b.unit.51">was</word>
<word id="le703040.b.unit.52">but</word>
<word id="le703040.b.unit.53">anyway</word>
<word id="le703040.b.unit.54">Saturday</word>
<word id="le703040.b.unit.55">morning</word>
<word id="le703040.b.unit.75">oh</word>
<word id="le703040.b.unit.76">no</word>
<word id="le703040.b.unit.77">not</word>
<word id="le703040.b.unit.78">Sunday</word>
<word id="le703040.b.unit.79">morning</word>
<word id="le703040.b.unit.80">Saturday</word>
<word id="le703040.b.unit.81">morning</word>
<word id="le703040.b.unit.82">i'm</word>
<word id="le703040.b.unit.83">confused</word>
<word id="le703040.b.unit.84">with</word>
<word id="le703040.b.unit.85">the</word>
<word id="le703040.b.unit.86">days</word>
<word id="le703040.b.unit.87">now</word>
<word id="le703040.b.unit.91">really</word>
<word id="le703040.b.unit.92">oh</word>
<word id="le703040.b.unit.93">you</word>
<word id="le703040.b.unit.94">sound</word>
<word id="le703040.b.unit.95">young</word>
<bcanchor id="le703040.bcanchorb.1"><nite:pointer href="le703040.a.lturn.xml#id(le703040.lturn.12.1)" role="bc"/></bcanchor>
<word id="le703040.b.unit.97">i</word>
<word id="le703040.b.unit.98">blame</word>
<word id="le703040.b.unit.99">me</word>
<word id="le703040.b.unit.100">age</word>
<word id="le703040.b.unit.101">dear</word>
<word id="le703040.b.unit.102">and</word>
<word id="le703040.b.unit.103">also</word>
<word id="le703040.b.unit.104">the</word>
<word id="le703040.b.unit.105">fact</word>
<word id="le703040.b.unit.106">that</word>
<word id="le703040.b.unit.107">i've</word>
<word id="le703040.b.unit.108">had</word>
<word id="le703040.b.unit.109">an</word>
<word id="le703040.b.unit.110">illness</word>
<word id="le703040.b.unit.111">that</word>
<word id="le703040.b.unit.112">makes</word>
<word id="le703040.b.unit.113">me</word>
<word id="le703040.b.unit.114">confused</word>
<word id="le703040.b.unit.128">they</word>
<word id="le703040.b.unit.129">blame</word>
<word id="le703040.b.unit.130">it</word>
<word id="le703040.b.unit.131">on</word>
<word id="le703040.b.unit.132">your</word>
<word id="le703040.b.unit.133">age</word>
<bcanchor id="le703040.bcanchorb.2"><nite:pointer href="le703040.a.lturn.xml#id(le703040.lturn.14.1)" role="bc"/></bcanchor>
<word id="le703040.b.unit.137">oh</word>
<word id="le703040.b.unit.138">you're</word>
<word id="le703040.b.unit.139">only</word>
<word id="le703040.b.unit.140">young</word>
<word id="le703040.b.unit.160">lovely</word>
<word id="le703040.b.unit.161">thank</word>
<word id="le703040.b.unit.162">you</word>
<word id="le703040.b.unit.163">very</word>
<word id="le703040.b.unit.164">much</word>
<word id="le703040.b.unit.169">bye</word>
<word id="le703040.b.unit.170">bye</word>
<comment text="end-ok" id="le703040.b.unit.171"/>
</nite:root>
