<?xml version="1.0" encoding="UTF-8"?>
<nite:root xmlns:nite="http://nite.sourceforge.net/" id="le707410.unit.a">
<stdzcode id="le707410.a.unit.1" description="name"/>
<pncode type="town" id="le707410.a.unit.11"/>
<pncode type="town" id="le707410.a.unit.12"/>
<pncode type="town" id="le707410.a.unit.13"/>
<sil BTlength="" id="le707410.a.unit.14"/>
<partword id="le707410.a.unit.15">pl</partword>
<word id="le707410.a.unit.28">right</word>
<word id="le707410.a.unit.29">you</word>
<word id="le707410.a.unit.30">need</word>
<word id="le707410.a.unit.31">to</word>
<word id="le707410.a.unit.32">speak</word>
<word id="le707410.a.unit.33">to</word>
<word id="le707410.a.unit.34">directory</word>
<word id="le707410.a.unit.35">enquiries</word>
<word id="le707410.a.unit.36">to</word>
<word id="le707410.a.unit.37">er</word>
<word id="le707410.a.unit.38">obtain</word>
<word id="le707410.a.unit.39">the</word>
<word id="le707410.a.unit.40">number</word>
<word id="le707410.a.unit.41">would</word>
<word id="le707410.a.unit.42">you</word>
<word id="le707410.a.unit.43">like</word>
<word id="le707410.a.unit.44">me</word>
<word id="le707410.a.unit.45">to</word>
<word id="le707410.a.unit.46">connect</word>
<word id="le707410.a.unit.60">yeah</word>
<word id="le707410.a.unit.61">i'll</word>
<word id="le707410.a.unit.62">connect</word>
<word id="le707410.a.unit.63">you</word>
<word id="le707410.a.unit.64">through</word>
</nite:root>
