<?xml version='1.0' encoding='UTF-8'?>
<nite:root xmlns:nite='http://nite.sourceforge.net/' id='le753220'>
<turn_pointer id='le753220.lturn_pointer.1'><nite:child href='le753220.a.lturn.xml#id(le753220.lturn.1)'/></turn_pointer>
<turn_pointer id='le753220.lturn_pointer.2'><nite:child href='le753220.b.lturn.xml#id(le753220.lturn.2)'/></turn_pointer>
<turn_pointer id='le753220.lturn_pointer.3'><nite:child href='le753220.a.lturn.xml#id(le753220.lturn.3)'/></turn_pointer>
<turn_pointer id='le753220.lturn_pointer.4'><nite:child href='le753220.b.lturn.xml#id(le753220.lturn.4)'/></turn_pointer>
<turn_pointer id='le753220.lturn_pointer.5'><nite:child href='le753220.a.lturn.xml#id(le753220.lturn.5)'/></turn_pointer>
<turn_pointer id='le753220.lturn_pointer.6'><nite:child href='le753220.b.lturn.xml#id(le753220.lturn.6)'/></turn_pointer>
<turn_pointer id='le753220.lturn_pointer.7'><nite:child href='le753220.a.lturn.xml#id(le753220.lturn.7)'/></turn_pointer>
</nite:root>
